wrap_pybind11/WrapPybind11.py
wrap_pybind11/WrapPybind11Exec.py
wrap_pybind11/__init__.py
wrap_pybind11/pywraptestlib.cpython-37m-darwin.so
wrap_pybind11/tests/PyWrapLibTests.py
wrap_pybind11/tests/__init__.py
wrap_pybind11-0.2.dist-info/METADATA
wrap_pybind11-0.2.dist-info/RECORD
wrap_pybind11-0.2.dist-info/WHEEL
wrap_pybind11-0.2.dist-info/entry_points.txt
wrap_pybind11-0.2.dist-info/top_level.txt
